Workbook

Sheet Cover
B3: NVIDIA CORPORATION
B4: Discounted Cash Flow Valuation Model
B5: As of LTM Q3 FY2026 | Ticker: NVDA | Exchange: NASDAQ
B8: TABLE OF CONTENTS
B9: 1. Assumptions | C9: All scenario drivers (Bear/Base/Bull), sourced and documented
B10: 2. Income Statement | C10: 5yr historical + 5yr projected, full margin build
B11: 3. Balance Sheet | C11: 5yr historical + 5yr projected, fully linked
B12: 4. Cash Flow Statement | C12: CFO/CFI/CFF, linked to all schedules
B13: 5. Working Capital Schedule | C13: DSO/DIO/DPO-driven AR, Inventory, AP
B14: 6. PP&E Schedule | C14: Capex and depreciation roll-forward
B15: 7. Debt Schedule | C15: Interest expense build
B16: 8. WACC | C16: Cost of equity (CAPM), after-tax cost of debt, capital weights
B17: 9. DCF | C17: FCFF build, discounting, EV-to-equity bridge
B18: 10. Terminal Value | C18: Perpetuity growth and exit multiple methods, cross-checked
B19: 11. Sensitivity | C19: WACC x terminal growth data table
B20: 12. Football Field / Output | C20: Summary valuation range vs. market price
B22: Prepared by: | C22: Date Completed
B23: Lewis Redmond | C23: 46191
B25: METHODOLOGY OVERVIEW
B26: This model values NVIDIA Corporation (NVDA) using a 5-year Discounted Cash Flow analysis (FY2027E-FY2031E), anchored to FY2026 reported financials. Free Cash Flow to the firm (FCFF) is projected under three scenarios (Bear/Base/Bull) and discounted at a WACC of 9.49%, reflecting NVIDIA's near-pure equity capital structure. Enterprise Value is bridged to Equity Value using FY2026A net cash of $54.1B. Terminal Value is estimated using both the Perpetuity Growth method (g=2.5%) and Exit Multiple method (11x EV/EBITDA), representing 73.8% of total Enterprise Value under the base case.

Sheet Assumptions
B1: 1. GLOBAL MODEL SETTINGS
B2: Active Scenario Switch (1=Bear, 2=Base, 3=Bull) | C2: 2
B3: Valuation Date | C3: Jan 25, 2026
D5: Bear | E5: Base | F5: Bull
B6: 2. REVENUE GROWTH DRIVERS | G6: Source
B7: Year 1 (FY2027E) Revenue Growth | C7: =CHOOSE($C$2, D7, E7, F7) -> 0.1 | D7: 0.06 | E7: 0.1 | F7: 0.14 | G7: NVIDIA FY2026 10-K consensus revenue estimates. 10% reflects continued Data Centre demand
B8: Year 2 (FY2028E) Revenue Growth | C8: =CHOOSE($C$2, D8, E8, F8) -> 0.09 | D8: 0.05 | E8: 0.09 | F8: 0.12 | G8: Growth deceleration assumption. Peer semiconductor revenue CAGR ~8-10%
B9: Year 3 (FY2029E) Revenue Growth | C9: =CHOOSE($C$2, D9, E9, F9) -> 0.08 | D9: 0.045 | E9: 0.08 | F9: 0.1 | G9: Fade toward terminal growth rate. Reflects law of large numbers on $215B base.
B10: Year 4 (FY2030E) Revenue Growth | C10: =CHOOSE($C$2, D10, E10, F10) -> 0.065 | D10: 0.035 | E10: 0.065 | F10: 0.08
B11: Year 5 (FY2031E) Revenue Growth | C11: =CHOOSE($C$2, D11, E11, F11) -> 0.05 | D11: 0.025 | E11: 0.05 | F11: 0.06
B13: 3. OPERATING COST MARGINS (% OF REVENUE) | G13: Source
B14: Target Gross Margin | C14: =CHOOSE($C$2,D14, E14, F14) -> 0.75 | D14: 0.7 | E14: 0.75 | F14: 0.8 | G14: FY2026A actual 71.1% (10-K). 75% reflects CUDA software mix shift, FY2025A was 75%.
B15: Target SG&A Margin | C15: =CHOOSE($C$2,D15, E15, F15) -> 0.03 | D15: 0.05 | E15: 0.03 | F15: 0.01 | G15: NVIDIA FY2022-2026 10K. 5yr historical average 3.2%. 3% reflects operating leverage
B16: Target R&D Margin | C16: =CHOOSE($C$2,D16, E16, F16) -> 0.09 | D16: 0.115 | E16: 0.09 | F16: 0.075 | G16: NVIDIA FY2022-2026 10K. FY2026A actual 8.6%. 9% reflects continued AI investment.
B17: Target Effective Tax Rate | C17: =CHOOSE($C$2,D17, E17, F17) -> 0.25 | D17: 0.25 | E17: 0.25 | F17: 0.25 | G17: US statutory 21%. Normalised rate 25% above statutory to account for state taxes and international. FY2026A effective rate 12.5% which is unusually low due to SBC deductions.
B19: 4. OPERATING WORKING CAPITAL DRIVERS | G19: Source
B20: Days Sales Outstanding (DSO) | C20: =CHOOSE($C$2, D20, E20, F20) -> 65 | D20: 75 | E20: 65 | F20: 55 | G20: AR/Revenue calculation from 10-K FY2022-2026. FY2026A actual DSO = 65 days. 5yr average 61 days.
B21: Days Inventory Outstanding (DIO) | C21: =CHOOSE($C$2, D21, E21, F21) -> 125 | D21: 140 | E21: 125 | F21: 110 | G21: Inventory/COGS calculation from 10-K FY2022-2026. FY2026A actual DIO = 125 days. 5yr average 123 days.
B22: Days Payable Outstanding (DPO) | C22: =CHOOSE($C$2, D22, E22, F22) -> 57 | D22: 50 | E22: 57 | F22: 65 | G22: AP/COGS calculation from 10-K FY2022-2026. FY2026A actual DPO = 57 days.
B24: 5. PP&E AND REINVESTMENT DRIVERS | G24: Source
B25: Capital Expenditures (Capex) as % of Revenue | C25: =CHOOSE($C$2, D25, E25, F25) -> 0.065 | D25: 0.08 | E25: 0.065 | F25: 0.04 | G25: FY2026 10-K CFS. FY2026A Capex $6,042M = 2.8% of revenue. 6.5% reflects AI infrastructure build-out cycle. FY2027E Capex/D&A ratio = 5.5x reflecting NVIDIA's accelerated AI infrastructure build-out. Ratio falls to 1.5x by FY2031E as PP&E base grows. In true steady-state the ratio approaches 1.0x, the 5-year horizon may not be sufficient to fully normalise this.
B26: Depreciation Rate (% of Beginning PP&E) | C26: =CHOOSE($C$2, D26, E26, F26) -> 0.27 | D26: 0.235 | E26: 0.27 | F26: 0.305 | G26: FY2026 10-K. Derived FY2026A D&A $2,843M / Beginning PP&E $6,283M = 45%. Used 27% as conservative estimate.
B28: 6. COST OF CAPITAL (WACC) INPUTS | G28: Source
B29: Risk-Free Rate (10-Year US Treasury Yield | C29: 0.04 | G29: US Treasury website / Bloomberg. US 10-Year Treasury yield as of January 25, 2026.
B30: Equity Risk Premium (ERP) | C30: 0.05 | G30: pages.stern.nyu.edu/~adamodar/. Damodaran implied ERP for US market.
B31: Relevered Beta (ϐ) | C31: 1.1 | G31: Damodaran industry betas. Relevered using semiconductor peer unleveraged beta.
B32: Pre-Tax Cost of Debt | C32: 0.055 | G32: FY2026 10-K. NVIDIA effective borrowing rate. FY2026A interest expense / average debt = approximately 5.5%.
B33: Market Value of Equity (Market Cap) | C33: 3300000 | G33: Yahoo Finance. NVIDIA market cap as of January 25, 2026.
B34: Market Value of Debt | C34: ='Balance Sheet'!G22+'Balance Sheet'!G24 -> 8468 | G34: FY2026 10-K BS. Total Debt = ST $999M + LT $7,469M = $8,468M.
B36: 7. VALUATION TERMINAL PARAMETERS | G36: Source
B37: Terminal Growth Rate (g) | C37: 0.025 | G37: CBO long-term projections. Long-run nominal US GDP growth. Within standard DCF range of 2-3%.
B38: Target Exit EBITDA Multiple (x) | C38: 11 | G38: Bloomberg consensus. Semiconductor peer median EV/EBITDA. Comparables: AMD, Broadcom, Qualcomm.
B39: Diluted Shares Outstanding | C39: 24440 | G39: FY2026 10-K. NVIDIA diluted shares outstanding.
B41: 8. BALANCE SHEET AUXILIARY DRIVERS
B42: Prepaid as % of Revenue | C42: =AVERAGE('Balance Sheet'!C9/'Income Statement'!C5,'Balance Sheet'!D9/'Income Statement'!D5,'Balance Sheet'!E9/'Income Statement'!E5,'Balance Sheet'!F9/'Income Statement'!F5,'Balance Sheet'!G9/'Income Statement'!G5) -> 0.027420704
B43: Accrued as % of Revenue | C43: =AVERAGE('Balance Sheet'!C21/'Income Statement'!C5,'Balance Sheet'!D21/'Income Statement'!D5,'Balance Sheet'!E21/'Income Statement'!E5,'Balance Sheet'!F21/'Income Statement'!F5,'Balance Sheet'!G21/'Income Statement'!G5) -> 0.10921249
B44: Other Assets as % of Revenue | C44: =AVERAGE('Balance Sheet'!C17/'Income Statement'!C5,'Balance Sheet'!D17/'Income Statement'!D5, 'Balance Sheet'!E17/'Income Statement'!E5,'Balance Sheet'!F17/'Income Statement'!F5,'Balance Sheet'!G17/'Income Statement'!G5) -> 0.083983689
B45: Other non-cash as % of Revenue | C45: =AVERAGE('Cash Flow Statement'!C8/'Income Statement'!C5, 'Cash Flow Statement'!D8/'Income Statement'!D5, 'Cash Flow Statement'!E8/'Income Statement'!E5, 'Cash Flow Statement'!F8/'Income Statement'!F5) -> -0.00028607897
B47: 9. AUDIT TRACE
B48: All Cell Documentation Complete | C48: =IF(COUNTA(G7,G8,G9,G14,G15,G16,G17,G20,G21,G22,G25,G26,G29,G30,G31,G32,G33,G34,G37,G38,G39) <20, "WARNING: Missing Sources", "Audit Trail OK") -> Audit Trail OK

Sheet Income Statement
C3: Historical | H3: Projected
B4: Item | C4: FY2022A | D4: FY2023A | E4: FY2024A | F4: FY2025A | G4: FY2026A | H4: FY2027E | I4: FY2028E | J4: FY2029E | K4: FY2030E | L4: FY2031E
B5: Revenue | C5: 26914 | D5: 26974 | E5: 60922 | F5: 130497 | G5: 215938 | H5: =G5*(1+Assumptions!$C$7) -> 237531.8 | I5: =H5*(1+Assumptions!$C$8) -> 258909.66 | J5: =I5*(1+Assumptions!$C$9) -> 279622.43 | K5: =J5*(1+Assumptions!$C$10) -> 297797.89 | L5: =K5*(1+Assumptions!$C$11) -> 312687.79
B6: % growth | C6: n/a | D6: =D5/C5-1 -> 0.002229323 | E6: =E5/D5-1 -> 1.2585453 | F6: =F5/E5-1 -> 1.1420341 | G6: =G5/F5-1 -> 0.65473536 | H6: =H5/G5-1 -> 0.1 | I6: =I5/H5-1 -> 0.09 | J6: =J5/I5-1 -> 0.08 | K6: =K5/J5-1 -> 0.065 | L6: =L5/K5-1 -> 0.05
B7: COGS | C7: 9439 | D7: 11618 | E7: 16621 | F7: 32639 | G7: 62475 | H7: =H5*(1-Assumptions!$C$14) -> 59382.95 | I7: =I5*(1-Assumptions!$C$14) -> 64727.416 | J7: =J5*(1-Assumptions!$C$14) -> 69905.609 | K7: =K5*(1-Assumptions!$C$14) -> 74449.473 | L7: =L5*(1-Assumptions!$C$14) -> 78171.947
B8: Gross Profit | C8: =C5-C7 -> 17475 | D8: =D5-D7 -> 15356 | E8: =E5-E7 -> 44301 | F8: =F5-F7 -> 97858 | G8: =G5-G7 -> 153463 | H8: =H5-H7 -> 178148.85 | I8: =I5-I7 -> 194182.25 | J8: =J5-J7 -> 209716.83 | ... L8: =L5-L7 -> 234515.84
B9: Gross Margin | C9: =C8/C5 -> 0.64929033 | D9: =D8/D5 -> 0.56928894 | E9: =E8/E5 -> 0.72717573 | F9: =F8/F5 -> 0.74988697 | G9: =G8/G5 -> 0.71068084 | H9: =H8/H5 -> 0.75 | I9: =I8/I5 -> 0.75 | J9: =J8/J5 -> 0.75 | ... L9: =L8/L5 -> 0.75
B10: SG&A | C10: 2166 | D10: 2440 | E10: 2654 | F10: 3491 | G10: 4579 | H10: =H5*Assumptions!$C$15 -> 7125.954 | I10: =I5*Assumptions!$C$15 -> 7767.2899 | J10: =J5*Assumptions!$C$15 -> 8388.673 | K10: =K5*Assumptions!$C$15 -> 8933.9368 | L10: =L5*Assumptions!$C$15 -> 9380.6336
B11: R&D | C11: 5268 | D11: 7339 | E11: 8675 | F11: 12914 | G11: 18497 | H11: =H5*Assumptions!$C$16 -> 21377.862 | I11: =I5*Assumptions!$C$16 -> 23301.87 | J11: =J5*Assumptions!$C$16 -> 25166.019 | K11: =K5*Assumptions!$C$16 -> 26801.81 | L11: =L5*Assumptions!$C$16 -> 28141.901
B12: Acquisition termination cost | C12: 0 | D12: 1353 | E12: 0 | F12: 0 | G12: 0 | H12: 0 | I12: 0 | J12: 0 | K12: 0 | L12: 0
B13: EBITDA | C13: =C8-C10-C11-C12 -> 10041 | D13: =D8-D10-D11-D12 -> 4224 | E13: =E8-E10-E11-E12 -> 32972 | F13: =F8-F10-F11-F12 -> 81453 | G13: =G8-G10-G11-G12 -> 130387 | H13: =H8-H10-H11-H12 -> 149645.03 | I13: =I8-I10-I11-I12 -> 163113.09 | J13: =J8-J10-J11-J12 -> 176162.13 | ... L13: =L8-L10-L11-L12 -> 196993.31
B14: EBITDA Margin | C14: =C13/C5 -> 0.37307721 | D14: =D13/D5 -> 0.15659524 | E14: =E13/E5 -> 0.54121664 | F14: =F13/F5 -> 0.62417527 | G14: =G13/G5 -> 0.60381684 | H14: =H13/H5 -> 0.63 | I14: =I13/I5 -> 0.63 | J14: =J13/J5 -> 0.63 | ... L14: =L13/L5 -> 0.63
B15: D&A | C15: 1174 | D15: 1554 | E15: 1508 | F15: 1864 | G15: 2843 | H15: ='PP&E Schedule'!H7 -> 2803.41 | I15: ='PP&E Schedule'!I7 -> 6215.1724 | J15: ='PP&E Schedule'!J7 -> 9080.9404 | K15: ='PP&E Schedule'!K7 -> 11536.46 | L15: ='PP&E Schedule'!L7 -> 13647.969
B16: EBIT | C16: =C13-C15 -> 8867 | D16: =D13-D15 -> 2670 | E16: =E13-E15 -> 31464 | F16: =F13-F15 -> 79589 | G16: =G13-G15 -> 127544 | H16: =H13-H15 -> 146841.62 | I16: =I13-I15 -> 156897.91 | J16: =J13-J15 -> 167081.19 | ... L16: =L13-L15 -> 183345.34
B17: EBIT Margin | C17: =C16/C5 -> 0.32945679 | D17: =D16/D5 -> 0.098984207 | E17: =E16/E5 -> 0.51646367 | F17: =F16/F5 -> 0.60989142 | G17: =G16/G5 -> 0.59065102 | H17: =H16/H5 -> 0.61819775 | I17: =I16/I5 -> 0.60599482 | J17: =J16/J5 -> 0.59752428 | ... L17: =L16/L5 -> 0.58635273
B18: Interest Expense | C18: -236 | D18: -262 | E18: -257 | F18: -247 | G18: -259 | H18: ='Debt Schedule'!$C$14 -> 465.74 | I18: ='Debt Schedule'!$C$14 -> 465.74 | J18: ='Debt Schedule'!$C$14 -> 465.74 | K18: ='Debt Schedule'!$C$14 -> 465.74 | L18: ='Debt Schedule'!$C$14 -> 465.74
B19: Interest Income | C19: 29 | D19: 267 | E19: 866 | F19: 1786 | G19: 2300 | H19: =H5*AVERAGE($G$19/$G$5,$F$19/$F$5,$E$19/$E$5,$D$19/$D$5) -> 2877.1433 | I19: =I5*AVERAGE($G$19/$G$5,$F$19/$F$5,$E$19/$E$5,$D$19/$D$5) -> 3136.0861 | J19: =J5*AVERAGE($G$19/$G$5,$F$19/$F$5,$E$19/$E$5,$D$19/$D$5) -> 3386.973 | K19: =K5*AVERAGE($G$19/$G$5,$F$19/$F$5,$E$19/$E$5,$D$19/$D$5) -> 3607.1263 | L19: =L5*AVERAGE($G$19/$G$5,$F$19/$F$5,$E$19/$E$5,$D$19/$D$5) -> 3787.4826
B20: Other income / expense | C20: 107 | D20: -48 | E20: 237 | F20: 1034 | G20: 9022 | H20: =H5*AVERAGE($F$20/$F$5,$E$20/$E$5,$D$20/$D$5,$C$20/$C$5) -> 831.94971 | I20: =I5*AVERAGE($F$20/$F$5,$E$20/$E$5,$D$20/$D$5,$C$20/$C$5) -> 906.82519 | J20: =J5*AVERAGE($F$20/$F$5,$E$20/$E$5,$D$20/$D$5,$C$20/$C$5) -> 979.3712 | K20: =K5*AVERAGE($F$20/$F$5,$E$20/$E$5,$D$20/$D$5,$C$20/$C$5) -> 1043.0303 | L20: =L5*AVERAGE($F$20/$F$5,$E$20/$E$5,$D$20/$D$5,$C$20/$C$5) -> 1095.1818
B21: Pre-Tax Income | C21: =C16+C18+C19+C20 -> 8767 | D21: =D16+D18+D19+D20 -> 2627 | E21: =E16+E18+E19+E20 -> 32310 | F21: =F16+F18+F19+F20 -> 82162 | G21: =G16+G18+G19+G20 -> 138607 | H21: =H16+H18+H19+H20 -> 151016.46 | I21: =I16+I18+I19+I20 -> 161406.57 | J21: =J16+J18+J19+J20 -> 171913.28 | ... L21: =L16+L18+L19+L20 -> 188693.74
B22: Taxes | C22: 189 | D22: -187 | E22: 4058 | F22: 11146 | G22: 21383 | H22: =H21*Assumptions!$C$17 -> 37754.114 | I22: =I21*Assumptions!$C$17 -> 40351.642 | J22: =J21*Assumptions!$C$17 -> 42978.319 | K22: =K21*Assumptions!$C$17 -> 45298.027 | L22: =L21*Assumptions!$C$17 -> 47173.435
B23: Net Income | C23: =C21-C22 -> 8578 | D23: =D21-D22 -> 2814 | E23: =E21-E22 -> 28252 | F23: =F21-F22 -> 71016 | G23: =G21-G22 -> 117224 | H23: =H21-H22 -> 113262.34 | I23: =I21-I22 -> 121054.92 | J23: =J21-J22 -> 128934.96 | ... L23: =L21-L22 -> 141520.31
B24: Net Income Margin | C24: =C23/C5 -> 0.31871888 | D24: =D23/D5 -> 0.10432268 | E24: =E23/E5 -> 0.46374052 | F24: =F23/F5 -> 0.54419642 | G24: =G23/G5 -> 0.54285952 | H24: =H23/H5 -> 0.47683023 | I24: =I23/I5 -> 0.46755661 | J24: =J23/J5 -> 0.46110377 | ... L24: =L23/L5 -> 0.45259301
B26: Gross margin is projected to expand from 71.1% in FY2026A to 75.0% by FY2027E, reflecting the shift from gaming GPUs towards high margin Data Centre and AI accelerator revenues as well as growing software and CUDA ecosystem licence revenues. This assumption is consistent with FY2025A actual growth margin of 75.0% and management's stated target of sustained 70%+ gross margins. EBITDA margin expands reaches 63.0% from FY2027E onwards as SG&A and R&D scale more slowly than revenue. This operating leverage assumption is the main driver of the forecasted FCFF growth

Sheet Balance Sheet
C2: Historical | H2: Projected
B3: Item | C3: FY2022A | D3: FY2023A | E3: FY2024A | F3: FY2025A | G3: FY2026A | H3: FY2027E | I3: FY2028E | J3: FY2029E | K3: FY2030E | L3: FY2031E
B4: ASSETS
A5: Current Assets | B5: Cash & Equivalents | C5: 1990 | D5: 3389 | E5: 7280 | F5: 8589 | G5: 10605 | H5: ='Balance Sheet'!$G5+'Cash Flow Statement'!H20 -> 107856.92 | I5: ='Balance Sheet'!$H5+'Cash Flow Statement'!I20 -> 213421.13 | J5: ='Balance Sheet'!$I5+'Cash Flow Statement'!J20 -> 328528.29 | K5: ='Balance Sheet'!$J5+'Cash Flow Statement'!K20 -> 452433.52 | L5: ='Balance Sheet'!$K5+'Cash Flow Statement'!L20 -> 583842.51
B6: Marketable securities | C6: 19218 | D6: 9907 | E6: 18704 | F6: 34621 | G6: 51951 | H6: ='Balance Sheet'!$G6 -> 51951 | I6: ='Balance Sheet'!$H6 -> 51951 | J6: ='Balance Sheet'!$I6 -> 51951 | K6: ='Balance Sheet'!$J6 -> 51951 | L6: ='Balance Sheet'!$K6 -> 51951
B7: Accounts Receivable | C7: 4650 | D7: 3827 | E7: 9999 | F7: 23065 | G7: 38466 | H7: ='Working Capital Schedule'!H5 -> 42300.184 | I7: ='Working Capital Schedule'!I5 -> 46107.2 | J7: ='Working Capital Schedule'!J5 -> 49795.776 | K7: ='Working Capital Schedule'!K5 -> 53032.502 | L7: ='Working Capital Schedule'!L5 -> 55684.127
B8: Inventory | C8: 2605 | D8: 5159 | E8: 5282 | F8: 10080 | G8: 21403 | H8: ='Working Capital Schedule'!H6 -> 20336.627 | I8: ='Working Capital Schedule'!I6 -> 22166.923 | J8: ='Working Capital Schedule'!J6 -> 23940.277 | K8: ='Working Capital Schedule'!K6 -> 25496.395 | L8: ='Working Capital Schedule'!L6 -> 26771.215
B9: Prepaid Expenses | C9: 366 | D9: 791 | E9: 3080 | F9: 3771 | G9: 3180 | H9: ='Income Statement'!H5*Assumptions!$C$42 -> 6513.2892 | I9: ='Income Statement'!I5*Assumptions!$C$42 -> 7099.4852 | J9: ='Income Statement'!J5*Assumptions!$C$42 -> 7667.444 | K9: ='Income Statement'!K5*Assumptions!$C$42 -> 8165.8279 | L9: ='Income Statement'!L5*Assumptions!$C$42 -> 8574.1193
B10: Total Current Assets | C10: =C5+C6+C7+C8+C9 -> 28829 | D10: =D5+D6+D7+D8+D9 -> 23073 | E10: =E5+E6+E7+E8+E9 -> 44345 | F10: =F5+F6+F7+F8+F9 -> 80126 | G10: =G5+G6+G7+G8+G9 -> 125605 | H10: =H5+H6+H7+H8+H9 -> 228958.02 | I10: =I5+I6+I7+I8+I9 -> 340745.74 | J10: =J5+J6+J7+J8+J9 -> 461882.79 | ... L10: =L5+L6+L7+L8+L9 -> 726822.97
A11: Non-Current Assets | B11: PP&E | C11: 2778 | D11: 3807 | E11: 3914 | F11: 6283 | G11: 10383 | H11: ='PP&E Schedule'!H8 -> 23019.157 | I11: ='PP&E Schedule'!I8 -> 33633.113 | J11: ='PP&E Schedule'!J8 -> 42727.63 | K11: ='PP&E Schedule'!K8 -> 50548.033 | L11: ='PP&E Schedule'!L8 -> 57224.771
B12: Operating lease assets | C12: 829 | D12: 1038 | E12: 1346 | F12: 1793 | G12: 2867 | H12: ='Balance Sheet'!$G12 -> 2867 | I12: ='Balance Sheet'!$H12 -> 2867 | J12: ='Balance Sheet'!$I12 -> 2867 | K12: ='Balance Sheet'!$J12 -> 2867 | L12: ='Balance Sheet'!$K12 -> 2867
B13: Intangible Assets | C13: 2339 | D13: 1676 | E13: 1112 | F13: 807 | G13: 3306 | H13: ='Balance Sheet'!$G13 -> 3306 | I13: ='Balance Sheet'!$H13 -> 3306 | J13: ='Balance Sheet'!$I13 -> 3306 | K13: ='Balance Sheet'!$J13 -> 3306 | L13: ='Balance Sheet'!$K13 -> 3306
B14: Goodwill | C14: 4349 | D14: 4372 | E14: 4430 | F14: 5188 | G14: 20832 | H14: ='Balance Sheet'!$G14 -> 20832 | I14: ='Balance Sheet'!$H14 -> 20832 | J14: ='Balance Sheet'!$I14 -> 20832 | K14: ='Balance Sheet'!$J14 -> 20832 | L14: ='Balance Sheet'!$K14 -> 20832
B15: Deferred income tax assets | C15: 1222 | D15: 3396 | E15: 6081 | F15: 10979 | G15: 13258 | H15: ='Balance Sheet'!$G15 -> 13258 | I15: ='Balance Sheet'!$H15 -> 13258 | J15: ='Balance Sheet'!$I15 -> 13258 | K15: ='Balance Sheet'!$J15 -> 13258 | L15: ='Balance Sheet'!$K15 -> 13258
B16: Non-marketable equity securities | C16: 0 | D16: 0 | E16: 0 | F16: 3387 | G16: 22251 | H16: ='Balance Sheet'!$G16 -> 22251 | I16: ='Balance Sheet'!$H16 -> 22251 | J16: ='Balance Sheet'!$I16 -> 22251 | K16: ='Balance Sheet'!$J16 -> 22251 | L16: ='Balance Sheet'!$K16 -> 22251
B17: Other assets | C17: 3841 | D17: 3820 | E17: 4500 | F17: 3038 | G17: 8301 | H17: ='Income Statement'!H5*Assumptions!$C$44 -> 19948.797 | I17: ='Income Statement'!I5*Assumptions!$C$44 -> 21744.188 | J17: ='Income Statement'!J5*Assumptions!$C$44 -> 23483.724 | K17: ='Income Statement'!K5*Assumptions!$C$44 -> 25010.166 | L17: ='Income Statement'!L5*Assumptions!$C$44 -> 26260.674
B18: Total Assets | C18: =C10+C11+C12+C13+C14+C15+C16+C17 -> 44187 | D18: =D10+D11+D12+D13+D14+D15+D16+D17 -> 41182 | E18: =E10+E11+E12+E13+E14+E15+E16+E17 -> 65728 | F18: =F10+F11+F12+F13+F14+F15+F16+F17 -> 111601 | G18: =G10+G11+G12+G13+G14+G15+G16+G17 -> 206803 | H18: =H10+H11+H12+H13+H14+H15+H16+H17 -> 334439.98 | I18: =I10+I11+I12+I13+I14+I15+I16+I17 -> 458637.04 | J18: =J10+J11+J12+J13+J14+J15+J16+J17 -> 590608.14 | ... L18: =L10+L11+L12+L13+L14+L15+L16+L17 -> 872822.42
B19: LIABILITIES
A20: Current Liabilities | B20: Accounts Payable | C20: 1783 | D20: 1193 | E20: 2699 | F20: 6310 | G20: 9812 | H20: ='Working Capital Schedule'!H7 -> 9273.5018 | I20: ='Working Capital Schedule'!I7 -> 10108.117 | J20: ='Working Capital Schedule'!J7 -> 10916.766 | K20: ='Working Capital Schedule'!K7 -> 11626.356 | L20: ='Working Capital Schedule'!L7 -> 12207.674
B21: Accrued Expenses | C21: 2552 | D21: 4120 | E21: 6682 | F21: 11737 | G21: 21352 | H21: ='Income Statement'!H5*Assumptions!$C$43 -> 25941.439 | I21: ='Income Statement'!I5*Assumptions!$C$43 -> 28276.169 | J21: ='Income Statement'!J5*Assumptions!$C$43 -> 30538.262 | K21: ='Income Statement'!K5*Assumptions!$C$43 -> 32523.249 | L21: ='Income Statement'!L5*Assumptions!$C$43 -> 34149.412
B22: Short-Term Debt | C22: 0 | D22: 1250 | E22: 1250 | F22: 0 | G22: 999 | H22: ='Balance Sheet'!$G22 -> 999 | I22: ='Balance Sheet'!$H22 -> 999 | J22: ='Balance Sheet'!$I22 -> 999 | K22: ='Balance Sheet'!$J22 -> 999 | L22: ='Balance Sheet'!$K22 -> 999
B23: Total Current Liabilities | C23: =C20+C21+C22 -> 4335 | D23: =D20+D21+D22 -> 6563 | E23: =E20+E21+E22 -> 10631 | F23: =F20+F21+F22 -> 18047 | G23: =G20+G21+G22 -> 32163 | H23: =H20+H21+H22 -> 36213.941 | I23: =I20+I21+I22 -> 39383.286 | J23: =J20+J21+J22 -> 42454.028 | ... L23: =L20+L21+L22 -> 47356.086
A24: Non-Current Liabilities | B24: Long-Term Debt | C24: 10946 | D24: 9703 | E24: 8459 | F24: 8463 | G24: 7469 | H24: ='Balance Sheet'!$G24 -> 7469 | I24: ='Balance Sheet'!$H24 -> 7469 | J24: ='Balance Sheet'!$I24 -> 7469 | K24: ='Balance Sheet'!$J24 -> 7469 | L24: ='Balance Sheet'!$K24 -> 7469
B25: Deferred Tax Liabilities | C25: 2294 | D25: 2815 | E25: 3660 | F25: 5764 | G25: 9878 | H25: ='Balance Sheet'!$G25 -> 9878 | I25: ='Balance Sheet'!$H25 -> 9878 | J25: ='Balance Sheet'!$I25 -> 9878 | K25: ='Balance Sheet'!$J25 -> 9878 | L25: ='Balance Sheet'!$K25 -> 9878
B26: Total Liabilities | C26: =C23+C24+C25 -> 17575 | D26: =D23+D24+D25 -> 19081 | E26: =E23+E24+E25 -> 22750 | F26: =F23+F24+F25 -> 32274 | G26: =G23+G24+G25 -> 49510 | H26: =H23+H24+H25 -> 53560.941 | I26: =I23+I24+I25 -> 56730.286 | J26: =J23+J24+J25 -> 59801.028 | ... L26: =L23+L24+L25 -> 64703.086
B27: EQUITY
B28: Common Stock | C28: 3 | D28: 2 | E28: 2 | F28: 24 | G28: 24 | H28: ='Balance Sheet'!$G28 -> 24 | I28: ='Balance Sheet'!$H28 -> 24 | J28: ='Balance Sheet'!$I28 -> 24 | K28: ='Balance Sheet'!$J28 -> 24 | L28: ='Balance Sheet'!$K28 -> 24
B29: Additional paid-in capital | C29: 10385 | D29: 11971 | E29: 13132 | F29: 11237 | G29: 10118 | H29: ='Balance Sheet'!$G29 -> 10118 | I29: ='Balance Sheet'!$H29 -> 10118 | J29: ='Balance Sheet'!$I29 -> 10118 | K29: ='Balance Sheet'!$J29 -> 10118 | L29: ='Balance Sheet'!$K29 -> 10118
B30: Accumulated other comprehensive loss | C30: -11 | D30: -43 | E30: 27 | F30: 28 | G30: 178 | H30: ='Balance Sheet'!$G30 -> 178 | I30: ='Balance Sheet'!$H30 -> 178 | J30: ='Balance Sheet'!$I30 -> 178 | K30: ='Balance Sheet'!$J30 -> 178 | L30: ='Balance Sheet'!$K30 -> 178
B31: Retained Earnings | C31: 16235 | D31: 10171 | E31: 29817 | F31: 68038 | G31: 146973 | H31: ='Balance Sheet'!$G31+'Income Statement'!H23 -> 260235.34 | I31: ='Balance Sheet'!$H31+'Income Statement'!I23 -> 381290.27 | J31: ='Balance Sheet'!$I31+'Income Statement'!J23 -> 510225.23 | K31: ='Balance Sheet'!$J31+'Income Statement'!K23 -> 646119.31 | L31: ='Balance Sheet'!$K31+'Income Statement'!L23 -> 787639.61
B32: Total Equity | C32: =C28+C29+C30+C31 -> 26612 | D32: =D28+D29+D30+D31 -> 22101 | E32: =E28+E29+E30+E31 -> 42978 | F32: =F28+F29+F30+F31 -> 79327 | G32: =G28+G29+G30+G31 -> 157293 | H32: =SUM(H28:H31) -> 270555.34 | I32: =SUM(I28:I31) -> 391610.27 | J32: =SUM(J28:J31) -> 520545.23 | K32: =SUM(K28:K31) -> 656439.31 | L32: =SUM(L28:L31) -> 797959.61
B34: BS Check | C34: =ROUND(C18-(C26+C32),2) -> 0 | D34: =ROUND(D18-(D26+D32),2) -> 0 | E34: =ROUND(E18-(E26+E32),2) -> 0 | F34: =ROUND(F18-(F26+F32),2) -> 0 | G34: =ROUND(G18-(G26+G32),2) -> 0 | H34: =ROUND(H18-(H26+H32),2) -> 10323.69 | I34: =ROUND(I18-(I26+I32),2) -> 10296.48 | J34: =ROUND(J18-(J26+J32),2) -> 10261.89 | ... L34: =ROUND(L18-(L26+L32),2) -> 10159.72

Sheet Cash Flow Statement
C2: Historical | H2: Projected
B3: Item | C3: FY2022A | D3: FY2023A | E3: FY2024A | F3: FY2025A | G3: FY2026A | H3: FY2027E | I3: FY2028E | J3: FY2029E | K3: FY2030E | L3: FY2031E
B4: CASH FLOW FROM OPERATIONS (CFO)
B5: Net Income | C5: ='Income Statement'!C23 -> 8578 | D5: ='Income Statement'!D23 -> 2814 | E5: ='Income Statement'!E23 -> 28252 | F5: ='Income Statement'!F23 -> 71016 | G5: ='Income Statement'!G23 -> 117224 | H5: ='Income Statement'!H23 -> 113262.34 | I5: ='Income Statement'!I23 -> 121054.92 | J5: ='Income Statement'!J23 -> 128934.96 | ... L5: ='Income Statement'!L23 -> 141520.31
B6: D&A | C6: ='Income Statement'!C15 -> 1174 | D6: ='Income Statement'!D15 -> 1554 | E6: ='Income Statement'!E15 -> 1508 | F6: ='Income Statement'!F15 -> 1864 | G6: ='Income Statement'!G15 -> 2843 | H6: ='Income Statement'!H15 -> 2803.41 | I6: ='Income Statement'!I15 -> 6215.1724 | J6: ='Income Statement'!J15 -> 9080.9404 | ... L6: ='Income Statement'!L15 -> 13647.969
B7: Changes in Working Capital | C7: -3276 | D7: =-('Balance Sheet'!$D7-'Balance Sheet'!$C7)-('Balance Sheet'!D8-'Balance Sheet'!C8)-('Balance Sheet'!D9-'Balance Sheet'!C9)+('Balance Sheet'!D20-'Balance Sheet'!C20)+('Balance Sheet'!D21-'Balance Sheet'!C21) -> -1178 | E7: =-('Balance Sheet'!$E7-'Balance Sheet'!$D7)-('Balance Sheet'!E8-'Balance Sheet'!D8)-('Balance Sheet'!E9-'Balance Sheet'!D9)+('Balance Sheet'!E20-'Balance Sheet'!D20)+('Balance Sheet'!E21-'Balance Sheet'!D21) -> -4516 | F7: =-('Balance Sheet'!$F7-'Balance Sheet'!$E7)-('Balance Sheet'!F8-'Balance Sheet'!E8)-('Balance Sheet'!F9-'Balance Sheet'!E9)+('Balance Sheet'!F20-'Balance Sheet'!E20)+('Balance Sheet'!F21-'Balance Sheet'!E21) -> -9889 | G7: =-('Balance Sheet'!$G7-'Balance Sheet'!$F7)-('Balance Sheet'!G8-'Balance Sheet'!F8)-('Balance Sheet'!G9-'Balance Sheet'!F9)+('Balance Sheet'!G20-'Balance Sheet'!F20)+('Balance Sheet'!G21-'Balance Sheet'!F21) -> -13016 | H7: =-'Working Capital Schedule'!H9 -> -3306.3085 | I7: =-'Working Capital Schedule'!I9 -> -4802.6978 | J7: =-'Working Capital Schedule'!J9 -> -4653.2805 | K7: =-'Working Capital Schedule'!K9 -> -4083.2536 | L7: =-'Working Capital Schedule'!L9 -> -3345.127
B8: Other non-cash adjustments | C8: -30 | D8: -32 | E8: 70 | F8: 1 | G8: 150 | H8: ='Income Statement'!H5*Assumptions!$C$45 -> -67.952852 | I8: ='Income Statement'!I5*Assumptions!$C$45 -> -74.068609 | J8: ='Income Statement'!J5*Assumptions!$C$45 -> -79.994097 | K8: ='Income Statement'!K5*Assumptions!$C$45 -> -85.193714 | L8: ='Income Statement'!L5*Assumptions!$C$45 -> -89.453399
B9: CFO | C9: =SUM(C5:C8) -> 6446 | D9: =SUM(D5:D8) -> 3158 | E9: =SUM(E5:E8) -> 25314 | F9: =SUM(F5:F8) -> 62992 | G9: =SUM(G5:G8) -> 107201 | H9: =SUM(H5:H8) -> 112691.49 | I9: =SUM(I5:I8) -> 122393.33 | J9: =SUM(J5:J8) -> 133282.62 | ... L9: =SUM(L5:L8) -> 151733.69
B10: CASH FLOW FROM INVESTING (CFI)
B11: Capital Expenditures | C11: -976 | D11: -1833 | E11: -1069 | F11: -3236 | G11: -6042 | H11: =-'PP&E Schedule'!H6 -> -15439.567 | I11: =-'PP&E Schedule'!I6 -> -16829.128 | J11: =-'PP&E Schedule'!J6 -> -18175.458 | K11: =-'PP&E Schedule'!K6 -> -19356.863 | L11: =-'PP&E Schedule'!L6 -> -20324.706
B12: Acquisitions/Divestitures | C12: -263 | D12: -49 | E12: -83 | F12: -1007 | G12: -1535 | H12: =0 -> 0 | I12: =0 -> 0 | J12: =0 -> 0 | K12: =0 -> 0 | L12: =0 -> 0
B13: Other investing activities | C13: 9311 | D13: =-('Balance Sheet'!D6-'Balance Sheet'!C6)-('Balance Sheet'!D16-'Balance Sheet'!C16) -> 9311 | E13: =-('Balance Sheet'!E6-'Balance Sheet'!D6)-('Balance Sheet'!E16-'Balance Sheet'!D16) -> -8797 | F13: =-('Balance Sheet'!F6-'Balance Sheet'!E6)-('Balance Sheet'!F16-'Balance Sheet'!E16) -> -19304 | G13: =-('Balance Sheet'!G6-'Balance Sheet'!F6)-('Balance Sheet'!G16-'Balance Sheet'!F16) -> -36194 | H13: =0 -> 0 | I13: =0 -> 0 | J13: =0 -> 0 | K13: =0 -> 0 | L13: =0 -> 0
B14: CFI | C14: =SUM(C11:C13) -> 8072 | D14: =SUM(D11:D13) -> 7429 | E14: =SUM(E11:E13) -> -9949 | F14: =SUM(F11:F13) -> -23547 | G14: =SUM(G11:G13) -> -43771 | H14: =SUM(H11:H13) -> -15439.567 | I14: =SUM(I11:I13) -> -16829.128 | J14: =SUM(J11:J13) -> -18175.458 | ... L14: =SUM(L11:L13) -> -20324.706
B15: CASH FLOW FROM FINANCING (CFF)
B16: Debt issuance/repayment | C16: -1000 | D16: 0 | E16: -1250 | F16: -1250 | G16: 0 | H16: =('Balance Sheet'!H24-'Balance Sheet'!G24)+('Balance Sheet'!H22-'Balance Sheet'!G22) -> 0 | I16: =('Balance Sheet'!I24-'Balance Sheet'!H24)+('Balance Sheet'!I22-'Balance Sheet'!H22) -> 0 | J16: =('Balance Sheet'!J24-'Balance Sheet'!I24)+('Balance Sheet'!J22-'Balance Sheet'!I22) -> 0 | K16: =('Balance Sheet'!K24-'Balance Sheet'!J24)+('Balance Sheet'!K22-'Balance Sheet'!J22) -> 0 | L16: =('Balance Sheet'!L24-'Balance Sheet'!K24)+('Balance Sheet'!L22-'Balance Sheet'!K22) -> 0
B17: Equity issuance/buybacks | C17: 281 | D17: -9684 | E17: -9130 | F17: -33216 | G17: -39442 | H17: 0 | I17: 0 | J17: 0 | K17: 0 | L17: 0
B18: Dividends paid | C18: -399 | D18: -398 | E18: -395 | F18: -834 | G18: -974 | H18: =0 -> 0 | I18: =0 -> 0 | J18: =0 -> 0 | K18: =0 -> 0 | L18: =0 -> 0
B19: CFF | C19: =SUM(C16:C18) -> -1118 | D19: =SUM(D16:D18) -> -10082 | E19: =SUM(E16:E18) -> -10775 | F19: =SUM(F16:F18) -> -35300 | G19: =SUM(G16:G18) -> -40416 | H19: =SUM(H16:H18) -> 0 | I19: =SUM(I16:I18) -> 0 | J19: =SUM(J16:J18) -> 0 | ... L19: =SUM(L16:L18) -> 0
B20: Net Change in Cash | C20: =C9+C14+C19 -> 13400 | D20: =D9+D14+D19 -> 505 | E20: =E9+E14+E19 -> 4590 | F20: =F9+F14+F19 -> 4145 | G20: =G9+G14+G19 -> 23014 | H20: =H9+H14+H19 -> 97251.924 | I20: =I9+I14+I19 -> 105564.2 | J20: =J9+J14+J19 -> 115107.17 | ... L20: =L9+L14+L19 -> 131408.99

Sheet Working Capital Schedule
C3: Historical | H3: Projected
B4: Item | C4: FY2022A | D4: FY2023A | E4: FY2024A | F4: FY2025A | G4: FY2026A | H4: FY2027E | I4: FY2028E | J4: FY2029E | K4: FY2030E | L4: FY2031E
B5: AR | C5: ='Balance Sheet'!C7 -> 4650 | D5: ='Balance Sheet'!D7 -> 3827 | E5: ='Balance Sheet'!E7 -> 9999 | F5: ='Balance Sheet'!F7 -> 23065 | G5: ='Balance Sheet'!G7 -> 38466 | H5: =(Assumptions!$C$20/365)*'Income Statement'!H5 -> 42300.184 | I5: =(Assumptions!$C$20/365)*'Income Statement'!I5 -> 46107.2 | J5: =(Assumptions!$C$20/365)*'Income Statement'!J5 -> 49795.776 | K5: =(Assumptions!$C$20/365)*'Income Statement'!K5 -> 53032.502 | L5: =(Assumptions!$C$20/365)*'Income Statement'!L5 -> 55684.127
B6: Inventory | C6: ='Balance Sheet'!C8 -> 2605 | D6: ='Balance Sheet'!D8 -> 5159 | E6: ='Balance Sheet'!E8 -> 5282 | F6: ='Balance Sheet'!F8 -> 10080 | G6: ='Balance Sheet'!G8 -> 21403 | H6: =(Assumptions!$C$21/365)*'Income Statement'!H7 -> 20336.627 | I6: =(Assumptions!$C$21/365)*'Income Statement'!I7 -> 22166.923 | J6: =(Assumptions!$C$21/365)*'Income Statement'!J7 -> 23940.277 | K6: =(Assumptions!$C$21/365)*'Income Statement'!K7 -> 25496.395 | L6: =(Assumptions!$C$21/365)*'Income Statement'!L7 -> 26771.215
B7: AP | C7: ='Balance Sheet'!C20 -> 1783 | D7: ='Balance Sheet'!D20 -> 1193 | E7: ='Balance Sheet'!E20 -> 2699 | F7: ='Balance Sheet'!F20 -> 6310 | G7: ='Balance Sheet'!G20 -> 9812 | H7: =(Assumptions!$C$22/365)*'Income Statement'!H7 -> 9273.5018 | I7: =(Assumptions!$C$22/365)*'Income Statement'!I7 -> 10108.117 | J7: =(Assumptions!$C$22/365)*'Income Statement'!J7 -> 10916.766 | K7: =(Assumptions!$C$22/365)*'Income Statement'!K7 -> 11626.356 | L7: =(Assumptions!$C$22/365)*'Income Statement'!L7 -> 12207.674
B8: Net Working Capital | C8: =C5+C6-C7 -> 5472 | D8: =D5+D6-D7 -> 7793 | E8: =E5+E6-E7 -> 12582 | F8: =F5+F6-F7 -> 26835 | G8: =G5+G6-G7 -> 50057 | H8: =H5+H6-H7 -> 53363.308 | I8: =I5+I6-I7 -> 58166.006 | J8: =J5+J6-J7 -> 62819.287 | ... L8: =L5+L6-L7 -> 70247.667
B9: Change in NWC | C9: n/a | D9: =D8-C8 -> 2321 | E9: =E8-D8 -> 4789 | F9: =F8-E8 -> 14253 | G9: =G8-F8 -> 23222 | H9: =H8-G8 -> 3306.3085 | I9: =I8-H8 -> 4802.6978 | J9: =J8-I8 -> 4653.2805 | K9: =K8-J8 -> 4083.2536 | L9: =L8-K8 -> 3345.127
B14: Item | C14: FY2022A | D14: FY2023A | E14: FY2024A | F14: FY2025A | G14: FY2026A | H14: FY2027E | I14: FY2028E | J14: FY2029E | K14: FY2030E | L14: FY2031E
B15: DSO (days) | C15: ='Balance Sheet'!C7/'Income Statement'!C5*365 -> 63.061975 | D15: ='Balance Sheet'!D7/'Income Statement'!D5*365 -> 51.785238 | E15: ='Balance Sheet'!E7/'Income Statement'!E5*365 -> 59.906684 | F15: ='Balance Sheet'!F7/'Income Statement'!F5*365 -> 64.512786 | G15: ='Balance Sheet'!G7/'Income Statement'!G5*365 -> 65.01908 | H15: =Assumptions!$C$20 -> 65 | I15: =Assumptions!$C$20 -> 65 | J15: =Assumptions!$C$20 -> 65 | K15: =Assumptions!$C$20 -> 65 | L15: =Assumptions!$C$20 -> 65
B16: DIO (days) | C16: ='Balance Sheet'!C8/'Income Statement'!C7*365 -> 100.73366 | D16: ='Balance Sheet'!D8/'Income Statement'!D7*365 -> 162.0791 | E16: ='Balance Sheet'!E8/'Income Statement'!E7*365 -> 115.99362 | F16: ='Balance Sheet'!F8/'Income Statement'!F7*365 -> 112.72404 | G16: ='Balance Sheet'!G8/'Income Statement'!G7*365 -> 125.04354 | H16: =Assumptions!$C$21 -> 125 | I16: =Assumptions!$C$21 -> 125 | J16: =Assumptions!$C$21 -> 125 | K16: =Assumptions!$C$21 -> 125 | L16: =Assumptions!$C$21 -> 125
B17: DPO (days) | C17: ='Balance Sheet'!C20/'Income Statement'!C7*365 -> 68.947452 | D17: ='Balance Sheet'!D20/'Income Statement'!D7*365 -> 37.480203 | E17: ='Balance Sheet'!E20/'Income Statement'!E7*365 -> 59.270501 | F17: ='Balance Sheet'!F20/'Income Statement'!F7*365 -> 70.564356 | G17: ='Balance Sheet'!G20/'Income Statement'!G7*365 -> 57.32501 | H17: =Assumptions!$C$22 -> 57 | I17: =Assumptions!$C$22 -> 57 | J17: =Assumptions!$C$22 -> 57 | K17: =Assumptions!$C$22 -> 57 | L17: =Assumptions!$C$22 -> 57

Sheet PP&E Schedule
C3: Historical | H3: Projected
B4: Item | C4: FY2022A | D4: FY2023A | E4: FY2024A | F4: FY2025A | G4: FY2026A | H4: FY2027E | I4: FY2028E | J4: FY2029E | K4: FY2030E | L4: FY2031E
B5: Beginning Net PP&E | C5: 0 | D5: ='Balance Sheet'!C11 -> 2778 | E5: ='Balance Sheet'!D11 -> 3807 | F5: ='Balance Sheet'!E11 -> 3914 | G5: ='Balance Sheet'!F11 -> 6283 | H5: ='Balance Sheet'!G11 -> 10383 | I5: =H8 -> 23019.157 | J5: =I8 -> 33633.113 | K5: =J8 -> 42727.63 | L5: =K8 -> 50548.033
B6: Capex | C6: =ABS('Cash Flow Statement'!C11) -> 976 | D6: =ABS('Cash Flow Statement'!D11) -> 1833 | E6: =ABS('Cash Flow Statement'!E11) -> 1069 | F6: =ABS('Cash Flow Statement'!F11) -> 3236 | G6: =ABS('Cash Flow Statement'!G11) -> 6042 | H6: =Assumptions!$C$25*'Income Statement'!H5 -> 15439.567 | I6: =Assumptions!$C$25*'Income Statement'!I5 -> 16829.128 | J6: =Assumptions!$C$25*'Income Statement'!J5 -> 18175.458 | K6: =Assumptions!$C$25*'Income Statement'!K5 -> 19356.863 | L6: =Assumptions!$C$25*'Income Statement'!L5 -> 20324.706
B7: Depreciation | C7: ='Income Statement'!C15 -> 1174 | D7: ='Income Statement'!D15 -> 1554 | E7: ='Income Statement'!E15 -> 1508 | F7: ='Income Statement'!F15 -> 1864 | G7: ='Income Statement'!G15 -> 2843 | H7: =H5*Assumptions!$C$26 -> 2803.41 | I7: =I5*Assumptions!$C$26 -> 6215.1724 | J7: =J5*Assumptions!$C$26 -> 9080.9404 | K7: =K5*Assumptions!$C$26 -> 11536.46 | L7: =L5*Assumptions!$C$26 -> 13647.969
B8: Ending Net PP&E | C8: ='Balance Sheet'!C11 -> 2778 | D8: ='Balance Sheet'!D11 -> 3807 | E8: ='Balance Sheet'!E11 -> 3914 | F8: ='Balance Sheet'!F11 -> 6283 | G8: ='Balance Sheet'!G11 -> 10383 | H8: =H5+H6-H7 -> 23019.157 | I8: =I5+I6-I7 -> 33633.113 | J8: =J5+J6-J7 -> 42727.63 | K8: =K5+K6-K7 -> 50548.033 | L8: =L5+L6-L7 -> 57224.771
B9: Capex/D&A | C9: =C6/C7 -> 0.83134583 | D9: =D6/D7 -> 1.1795367 | E9: =E6/E7 -> 0.70888594 | F9: =F6/F7 -> 1.7360515 | G9: =G6/G7 -> 2.1252198 | H9: =H6/H7 -> 5.5074238 | I9: =I6/I7 -> 2.7077492 | J9: =J6/J7 -> 2.0014952 | ... L9: =L6/L7 -> 1.489211

Sheet Debt Schedule
B4: Item | C4: Value
B5: Beginning LT Debt | C5: ='Balance Sheet'!G24 -> 7469
B6: Repayments | C6: =0 -> 0
B7: New Issuances | C7: =0 -> 0
B8: Ending LT Debt | C8: =C5+C6+C7 -> 7469
B9: Beginning ST Debt | C9: ='Balance Sheet'!G22 -> 999
B10: Repayments | C10: =0 -> 0
B11: Ending ST Debt | C11: =C9+C10 -> 999
B12: Total Debt | C12: =C8+C11 -> 8468
B13: Interest Rate | C13: =Assumptions!$C$32 -> 0.055
B14: Interest Expense | C14: =C12*C13 -> 465.74

Sheet WACC
H3: Projected
G4: Item | H4: FY2027E | I4: FY2028E | J4: FY2029E | K4: FY2030E | L4: FY2031E
G5: Cost of Equity (Re) | H5: =Assumptions!$C$29+Assumptions!$C$31*Assumptions!$C$30 -> 0.095 | I5: =Assumptions!$C$29+Assumptions!$C$31*Assumptions!$C$30 -> 0.095 | J5: =Assumptions!$C$29+Assumptions!$C$31*Assumptions!$C$30 -> 0.095 | K5: =Assumptions!$C$29+Assumptions!$C$31*Assumptions!$C$30 -> 0.095 | L5: =Assumptions!$C$29+Assumptions!$C$31*Assumptions!$C$30 -> 0.095
G6: After-Tax Cost of Debt | H6: =Assumptions!$C$32*(1-Assumptions!$C$17) -> 0.04125 | I6: =Assumptions!$C$32*(1-Assumptions!$C$17) -> 0.04125 | J6: =Assumptions!$C$32*(1-Assumptions!$C$17) -> 0.04125 | K6: =Assumptions!$C$32*(1-Assumptions!$C$17) -> 0.04125 | L6: =Assumptions!$C$32*(1-Assumptions!$C$17) -> 0.04125
G7: E/V | H7: =Assumptions!$C$33/(Assumptions!$C$33+Assumptions!$C$34) -> 0.99744051 | I7: =Assumptions!$C$33/(Assumptions!$C$33+Assumptions!$C$34) -> 0.99744051 | J7: =Assumptions!$C$33/(Assumptions!$C$33+Assumptions!$C$34) -> 0.99744051 | K7: =Assumptions!$C$33/(Assumptions!$C$33+Assumptions!$C$34) -> 0.99744051 | L7: =Assumptions!$C$33/(Assumptions!$C$33+Assumptions!$C$34) -> 0.99744051
G8: D/V | H8: =Assumptions!$C$34/(Assumptions!$C$33+Assumptions!$C$34) -> 0.0025594928 | I8: =Assumptions!$C$34/(Assumptions!$C$33+Assumptions!$C$34) -> 0.0025594928 | J8: =Assumptions!$C$34/(Assumptions!$C$33+Assumptions!$C$34) -> 0.0025594928 | K8: =Assumptions!$C$34/(Assumptions!$C$33+Assumptions!$C$34) -> 0.0025594928 | L8: =Assumptions!$C$34/(Assumptions!$C$33+Assumptions!$C$34) -> 0.0025594928
G9: WACC (Sensitivity Overide) | H9: =IF(Sensitivity!$K$2<>"",Sensitivity!$K$2,(H7*H5)+(H8*H6)) -> 0.09486 | I9: =IF(Sensitivity!$K$2<>"",Sensitivity!$K$2,(I7*I5)+(I8*I6)) -> 0.09486 | J9: =IF(Sensitivity!$K$2<>"",Sensitivity!$K$2,(J7*J5)+(J8*J6)) -> 0.09486 | K9: =IF(Sensitivity!$K$2<>"",Sensitivity!$K$2,(K7*K5)+(K8*K6)) -> 0.09486 | L9: =IF(Sensitivity!$K$2<>"",Sensitivity!$K$2,(L7*L5)+(L8*L6)) -> 0.09486
G10: WACC (Base Case Used in DCF) | H10: =(H7*H5)+(H8*H6) -> 0.094862427 | I10: =(I7*I5)+(I8*I6) -> 0.094862427 | J10: =(J7*J5)+(J8*J6) -> 0.094862427 | K10: =(K7*K5)+(K8*K6) -> 0.094862427 | L10: =(L7*L5)+(L8*L6) -> 0.094862427
G12: WACC of 9.49% is effectively equal to the cost of equity at 9.50%, as debt is only 0.26% of total capital currently. This means the model's discount rate is almost entirely determined by three inputs: risk-free rate (4.0%), equity risk premium (5.0%) and beta (1.10). The near zero debt weighting also means the pre-tax cost of debt (5.5%) and the tax shield are irrelevant to the WACC output with a 1 percent change in cost of debt changing WACC by less than 0.01 percent.

Sheet DCF
C3: Historical | H3: Projected
B4: Item | C4: FY2022A | D4: FY2023A | E4: FY2024A | F4: FY2025A | G4: FY2026A | H4: FY2027E | I4: FY2028E | J4: FY2029E | K4: FY2030E | L4: FY2031E
B5: EBIT | C5: ='Income Statement'!C16 -> 8867 | D5: ='Income Statement'!D16 -> 2670 | E5: ='Income Statement'!E16 -> 31464 | F5: ='Income Statement'!F16 -> 79589 | G5: ='Income Statement'!G16 -> 127544 | H5: ='Income Statement'!H16 -> 146841.62 | I5: ='Income Statement'!I16 -> 156897.91 | J5: ='Income Statement'!J16 -> 167081.19 | ... L5: ='Income Statement'!L16 -> 183345.34
B6: NOPAT | H6: =H5*(1-Assumptions!$C$17) -> 110131.22 | I6: =I5*(1-Assumptions!$C$17) -> 117673.44 | J6: =J5*(1-Assumptions!$C$17) -> 125310.9 | K6: =K5*(1-Assumptions!$C$17) -> 132057.16 | L6: =L5*(1-Assumptions!$C$17) -> 137509 | M6: For reference only
B7: D&A | C7: ='Cash Flow Statement'!C6 -> 1174 | D7: ='Cash Flow Statement'!D6 -> 1554 | E7: ='Cash Flow Statement'!E6 -> 1508 | F7: ='Cash Flow Statement'!F6 -> 1864 | G7: ='Cash Flow Statement'!G6 -> 2843 | H7: ='Cash Flow Statement'!H6 -> 2803.41 | I7: ='Cash Flow Statement'!I6 -> 6215.1724 | J7: ='Cash Flow Statement'!J6 -> 9080.9404 | ... L7: ='Cash Flow Statement'!L6 -> 13647.969
B8: Capex | C8: ='PP&E Schedule'!C6 -> 976 | D8: ='PP&E Schedule'!D6 -> 1833 | E8: ='PP&E Schedule'!E6 -> 1069 | F8: ='PP&E Schedule'!F6 -> 3236 | G8: ='PP&E Schedule'!G6 -> 6042 | H8: ='PP&E Schedule'!H6 -> 15439.567 | I8: ='PP&E Schedule'!I6 -> 16829.128 | J8: ='PP&E Schedule'!J6 -> 18175.458 | ... L8: ='PP&E Schedule'!L6 -> 20324.706
B9: Change in NWC | D9: ='Working Capital Schedule'!D9 -> 2321 | E9: ='Working Capital Schedule'!E9 -> 4789 | F9: ='Working Capital Schedule'!F9 -> 14253 | G9: ='Working Capital Schedule'!G9 -> 23222 | H9: ='Working Capital Schedule'!H9 -> 3306.3085 | I9: ='Working Capital Schedule'!I9 -> 4802.6978 | J9: ='Working Capital Schedule'!J9 -> 4653.2805 | K9: ='Working Capital Schedule'!K9 -> 4083.2536 | L9: ='Working Capital Schedule'!L9 -> 3345.127
B10: FCFF | H10: =H6+H7-H8-H9 -> 94188.753 | I10: =I6+I7-I8-I9 -> 102256.78 | J10: =J6+J7-J8-J9 -> 111563.1 | K10: =K6+K7-K8-K9 -> 120153.5 | L10: =L6+L7-L8-L9 -> 127487.14 | M10: For reference only
B11: Discount Period | C11: - | D11: - | E11: - | F11: - | G11: - | H11: 1 | I11: 2 | J11: 3 | K11: 4 | L11: 5
B12: Discount Factor | H12: =1/(1+WACC!H9)^H11 -> 0.91335879 | I12: =1/(1+WACC!I9)^I11 -> 0.83422427 | J12: =1/(1+WACC!J9)^J11 -> 0.76194607 | K12: =1/(1+WACC!K9)^K11 -> 0.69593013 | L12: =1/(1+WACC!L9)^L11 -> 0.6356339
B13: PV of FCFF | H13: =H10*H12 -> 86028.125 | I13: =I10*I12 -> 85305.09 | J13: =J10*J12 -> 85005.063 | K13: =K10*K12 -> 83618.443 | L13: =L10*L12 -> 81035.148
B14: Sum of PV | C14: =SUM(H13:L13) -> 420991.87
B15: Enterprise Value | C15: =C14+'Terminal Value'!C10 -> 1609955.9
B16: Cash | C16: ='Balance Sheet'!C5+'Balance Sheet'!C6 -> 21208 | D16: ='Balance Sheet'!D5+'Balance Sheet'!D6 -> 13296 | E16: ='Balance Sheet'!E5+'Balance Sheet'!E6 -> 25984 | F16: ='Balance Sheet'!F5+'Balance Sheet'!F6 -> 43210 | G16: ='Balance Sheet'!G5+'Balance Sheet'!G6 -> 62556 | H16: ='Balance Sheet'!H5+'Balance Sheet'!H6 -> 159807.92 | I16: ='Balance Sheet'!I5+'Balance Sheet'!I6 -> 265372.13 | J16: ='Balance Sheet'!J5+'Balance Sheet'!J6 -> 380479.29 | ... L16: ='Balance Sheet'!L5+'Balance Sheet'!L6 -> 635793.51
B17: Total Debt | C17: ='Balance Sheet'!C22+'Balance Sheet'!C24 -> 10946 | D17: ='Balance Sheet'!D22+'Balance Sheet'!D24 -> 10953 | E17: ='Balance Sheet'!E22+'Balance Sheet'!E24 -> 9709 | F17: ='Balance Sheet'!F22+'Balance Sheet'!F24 -> 8463 | G17: ='Balance Sheet'!G22+'Balance Sheet'!G24 -> 8468 | H17: ='Balance Sheet'!H22+'Balance Sheet'!H24 -> 8468 | I17: ='Balance Sheet'!I22+'Balance Sheet'!I24 -> 8468 | J17: ='Balance Sheet'!J22+'Balance Sheet'!J24 -> 8468 | ... L17: ='Balance Sheet'!L22+'Balance Sheet'!L24 -> 8468
B18: Equity Value | C18: =C15+C16-C17 -> 1620217.9 | D18: =$C15+D16-D17 -> 1612298.9 | E18: =$C15+E16-E17 -> 1626230.9 | F18: =$C15+F16-F17 -> 1644702.9 | G18: =$C15+G16-G17 -> 1664043.9 | H18: =$C15+H16-H17 -> 1761295.8 | I18: =$C15+I16-I17 -> 1866860 | J18: =$C15+J16-J17 -> 1981967.2 | K18: =$C15+K16-K17 -> 2105872.4 | L18: =$C15+L16-L17 -> 2237281.4
B19: Diluted Shares Outstanding | C19: =Assumptions!$C$39 -> 24440 | D19: =Assumptions!$C$39 -> 24440 | E19: =Assumptions!$C$39 -> 24440 | F19: =Assumptions!$C$39 -> 24440 | G19: =Assumptions!$C$39 -> 24440 | H19: =Assumptions!$C$39 -> 24440 | I19: =Assumptions!$C$39 -> 24440 | J19: =Assumptions!$C$39 -> 24440 | ... L19: =Assumptions!$C$39 -> 24440
B20: Implied Share Prices | C20: =C18/C19 -> 66.293694 | D20: =D18/D19 -> 65.969676 | E20: =E18/E19 -> 66.539725 | F20: =F18/F19 -> 67.295535 | G20: =G18/G19 -> 68.086902 | H20: =H18/H19 -> 72.066113 | I20: =I18/I19 -> 76.385434 | J20: =J18/J19 -> 81.09522 | ... L20: =L18/L19 -> 91.541792
B21: EV (Exit Multiple Method) | C21: =C14+'Terminal Value'!C14 -> 1798363.7
B22: Equity Value (Exit) | C22: =C21+G16-G17 -> 1852451.7
B23: Implied Share Price (Exit) | C23: =C22/C19 -> 75.795897
B25: FCFF grows from $94,189M in FY2027E to $127,487M in FY2031, a 5-year CAGR of 7.7%, reflecting relatively stable FCF conversion. The primary drag on FCF conversion is capital expenditure (6.5% of revenue), which in FY2027E produces Capex of $15,440M against Depreciation of only $2,803M, a 5.5x ratio reflecting NVIDIA's accelerated AI infrastructure investment cycle. This ratio narrows to 1.5x by FY2031E as the PP&E base grows, but true steady-state is not reached within the forecast period, suggesting terminal year FCF may still incorporate above maintenance reinvestment. Working capital is a modest drag consuming $3,306M to $4,803M of cash annually as the business scales and receivables, inventory and payables grow proportionally.
B32: Item | C32: Value | D32: Type | G32: Item | H32: FY2027E | I32: FY2028E | J32: FY2029E | K32: FY2030E | L32: FY2031E
B33: Sum of PV FCFs | C33: =C14 -> 420991.87 | D33: Increase | G33: NOPAT | H33: =H6 -> 110131.22 | I33: =I6 -> 117673.44 | J33: =J6 -> 125310.9 | K33: =K6 -> 132057.16 | L33: =L6 -> 137509
B34: PV of TV | C34: ='Terminal Value'!C10 -> 1188964 | D34: Increase | G34: Add: D&A | H34: =H7 -> 2803.41 | I34: =I7 -> 6215.1724 | J34: =J7 -> 9080.9404 | K34: =K7 -> 11536.46 | L34: =L7 -> 13647.969
B35: Enterprise | C35: =C15 -> 1609955.9 | D35: Total | G35: Less: Capex | H35: =-H8 -> -15439.567 | I35: =-I8 -> -16829.128 | J35: =-J8 -> -18175.458 | K35: =-K8 -> -19356.863 | L35: =-L8 -> -20324.706
B36: Cash | C36: =G16 -> 62556 | D36: Increase | G36: Less: Change in NWC | H36: =-H9 -> -3306.3085 | I36: =-I9 -> -4802.6978 | J36: =-J9 -> -4653.2805 | K36: =-K9 -> -4083.2536 | L36: =-L9 -> -3345.127
B37: Debt | C37: =-G17 -> -8468 | D37: Decrease | G37: FCFF | H37: =H10 -> 94188.753 | I37: =I10 -> 102256.78 | J37: =J10 -> 111563.1 | K37: =K10 -> 120153.5 | L37: =L10 -> 127487.14
B38: Equity Value | C38: =G18 -> 1664043.9 | D38: Total

Sheet Terminal Value
B4: Item | C4: Value
B5: Last Year FCFF | C5: =DCF!L10 -> 127487.14
B6: Terminal Growth Rate | C6: =Sensitivity!$K$3 -> 0.025
B7: WACC | C7: =WACC!L9 -> 0.09486
B8: TV - Perpetuity Growth | C8: =C5*(1+C6)/(C7-C6) -> 1870517
B9: Last year Discount Factor | C9: =DCF!L12 -> 0.6356339
B10: PV of TV (Perpetuity) | C10: =C8*C9 -> 1188964
B11: Last year EBITDA | C11: ='Income Statement'!L13 -> 196993.31
B12: Exit Multiple | C12: =Assumptions!$C$38 -> 11
B13: TV - Exit Multiple | C13: =C12*C11 -> 2166926.4
B14: PV of TV (Exit Multiple) | C14: =C13*C9 -> 1377371.9
B15: Implied g (from Exit Multiple TV) | C15: =(C13*C7-C5)/(C13+C5) -> 0.034025034 | D15: =IF(C15>0.03,"WARNING: Implied g exceeds 3% ceiling","OK") -> WARNING: Implied g exceeds 3% ceiling
B17: Terminal Value represents 73.8% of Enterprise Value under the perpetuity growth method, consistent with the typical 60-80% range for established businesses with stable long-term economics. The 2.5% terminal growth rate is deliberately anchored to long-run US nominal GDP growth, acknowledging that no company can sustain above-economy growth indefinitely. The exit multiple method (11x EV/EBITDA) implies a perpetuity growth rate of 3.403%, marginally above the 3% ceiling, suggesting the exit multiple is slightly aggressive relative to the perpetuity assumption. The perpetuity growth method is treated as the primary output for conservatism. The spread between the two methods ($68.08 vs $75.80 per share) represents the terminal value uncertainty range and should be treated as a valuation band rather than two independent point estimates.

Sheet Sensitivity
C2: WACC vs Terminal Growth -> Implied Share Price | J2: WACC Override | K2: 0.09486
C3: =DCF!H20 -> 72.066113 | D3: 0.07425 | E3: 0.08425 | F3: 0.09486 | G3: 0.10486 | H3: 0.11486 | J3: Terminal Growth Override | K3: 0.025
C4: 0.015 | D4: 86.887375 | E4: 74.948163 | F4: 65.559231 | G4: 58.747203 | H4: 53.305735
C5: 0.02 | D5: 92.980298 | E5: 79.189713 | F5: 68.595371 | G5: 61.042488 | H5: 55.088029
C6: 0.025 | D6: 100.31036 | E6: 84.147135 | F6: 72.066113 | G6: 63.625188 | H6: 57.068663
C7: 0.03 | D7: 109.29694 | E7: 90.018369 | F7: 76.071969 | G7: 66.552891 | H7: 59.282698
C8: 0.035 | D8: 120.57309 | E8: 97.081731 | F8: 80.747029 | G8: 69.899675 | H8: 61.773972
C10: The sensitivity analysis confirms that NVIDIA's DCF valuation is most sensitive to the terminal growth rate. Moving from 1.5% to 3.5% terminal growth (at base case WACC of 9.49%) expands the implied share price from approximately $66 to $81. WACC sensitivity is comparably significant: moving from 7.49% to 11.49% (at base case growth of 2.5%) compresses the implied share price from $100.31 to $57.07. Critically, even at the most favourable corner of the matrix, the implied share price remains far below the current market price of $207.41, confirming that NVIDIA trades at a significant premium to a standard 5-year DCF intrinsic value under every modelled scenario.

Sheet Football Field 
B3: Method | C3: Low | D3: High | E3: Range
B4: DCF (Perpetuity Growth) | C4: =DCF!H20*0.9 -> 64.859502 | D4: =DCF!H20*1.1 -> 79.272725 | E4: =D4-C4 -> 14.413223
B5: DCF (Exit Multiple) | C5: =DCF!C23*0.9 -> 68.216308 | D5: =DCF!C23*1.1 -> 83.375487 | E5: =D5-C5 -> 15.159179
B6: Current Price | C6: 207.41 | D6: 207.41 | E6: 0.5
